{"structures": {"6": {"name": "135x20 MBB", "file": "135x20 MBB.npz", "dims": {"l": 135, "w": 20, "d": 1}, "EA": 1000.0, "dim": 2, "n_nodes": 2700, "n_edges": 10337, "date": "2026-02-27T20:48:20.022408"}, "7": {"name": "135x20 Zum Fertig Optimieren", "file": "135x20 Zum Fertig Optimieren.npz", "dims": {"l": 135, "w": 20, "d": 1}, "EA": 1000.0, "dim": 2, "n_nodes": 2079, "n_edges": 7238, "date": "2026-02-27T20:52:08.322439"}, "9": {"name": "30x7x7 Basis", "file": "30x7x7 Basis.npz", "dims": {"l": 30, "w": 7, "d": 7}, "EA": 1000.0, "dim": 3, "n_nodes": 1470, "n_edges": 12017, "date": "2026-02-27T20:58:43.039260"}}}